.coveragerc
.travis.yml
AUTHORS
ChangeLog
LICENSE
MANIFEST.in
README.rst
requirements.txt
setup.cfg
setup.py
tox.ini
docs/Makefile
docs/make.bat
docs/source/conf.py
docs/source/index.rst
docs/source/readme.rst
leonardo_slack/__init__.py
leonardo_slack/models.py
leonardo_slack/settings.py
leonardo_slack.egg-info/PKG-INFO
leonardo_slack.egg-info/SOURCES.txt
leonardo_slack.egg-info/dependency_links.txt
leonardo_slack.egg-info/not-zip-safe
leonardo_slack.egg-info/pbr.json
leonardo_slack.egg-info/requires.txt
leonardo_slack.egg-info/top_level.txt
leonardo_slack/apps/__init__.py
leonardo_slack/migrations/__init__.py
leonardo_slack/templates/slack/base.slack
leonardo_slack/widget/__init__.py
requirements/default.txt
requirements/tests.txt
tests/cov.sh
tests/local_settings.py
tests/manage.py
tests/testapp/__init__.py
tests/testapp/models.py
tests/testapp/settings.py
tests/testapp/urls.py
tests/testapp/tests/__init__.py
tests/testapp/tests/test_commands.py